{"sections":{"main":{"type":"main-page","disabled":true,"settings":{"show_title":true,"page_width":"xs"}},"b40ecaca-8930-44d2-b329-927a7eb05f05":{"type":"page-text-header","settings":{"show_breadcrumbs":true,"breadcrumb_color":"#333333","heading_1":"TRAINING","heading_2":"","subheading":"EVERYTHING YOU NEED TO KNOW ABOUT USING OUR PRODUCTS","body":"Our user-generated content shows you a customer's view on our products.","background_color":"#eae9e8","heading_color":"#333333","heading_2_color":"#ea2d24","subheading_color":"#333333","body_color":"#333333"}},"86e20185-14f4-49c7-8d48-b5b46263a128":{"type":"video-grid","blocks":{"c837cd19-ae25-483b-b125-5e1111fb2ea7":{"type":"video","settings":{"thumbnail_image":"shopify:\/\/shop_images\/EZYDOG_LONG_LEAD_BROLL_VIDEO_111223_FINAL_97ac58fb-12fb-47d3-999c-eb7aa4b7922d.gif","video_url":"shopify:\/\/pages\/track-n-train-leash-training","category":"AS SEEN ON","category_url":"shopify:\/\/pages\/track-n-train-leash-training","video_description":"Training with the Track 'n' Train Leash"}},"b0851cfe-b4c2-4e15-ad4d-3c862a805c9f":{"type":"video","settings":{"thumbnail_image":"shopify:\/\/shop_images\/crosscheck_training_video_1d14e043-2e6c-4d0b-99d9-310bb67e33e4.gif","video_url":"shopify:\/\/pages\/crosscheck-training-video","category":"AS SEEN ON","category_url":"shopify:\/\/pages\/crosscheck-training-video","video_description":"Training with the Crosscheck Harness"}},"a0de07d7-6fd5-4697-9999-39b94d061536":{"type":"video","settings":{"thumbnail_image":"shopify:\/\/shop_images\/dr_david_express_harness_1.gif","video_url":"shopify:\/\/pages\/dr-david-explains-why-ezydog-products-are-the-best","category":"AS SEEN ON","category_url":"shopify:\/\/pages\/dr-david-explains-why-ezydog-products-are-the-best","video_description":"Dr David explains why our Products are so good."}},"bae59929-35c2-4b81-92eb-1611a576a29f":{"type":"video","settings":{"thumbnail_image":"shopify:\/\/shop_images\/All_Training_Harnesses.gif","video_url":"shopify:\/\/pages\/training-harnesses","category":"AS SEEN ON","category_url":"shopify:\/\/pages\/training-harnesses","video_description":"Which harnesses to use for Training."}},"60e41ea9-c86b-4f06-ac89-7065175dd961":{"type":"video","settings":{"thumbnail_image":"shopify:\/\/shop_images\/herbert_and_clover_slimline.gif","video_url":"shopify:\/\/pages\/using-the-new-long-leash","category":"AS SEEN ON","category_url":"shopify:\/\/pages\/using-the-new-long-leash","video_description":"Clover enjoys the New Slimline Leash"}},"368df2ce-360f-48e8-a858-89226e0db833":{"type":"video","settings":{"thumbnail_image":"shopify:\/\/shop_images\/SLIMLINE_UGC_NEW_VIDEO_27.11.23_7b8aa7f7-9959-49b8-bacc-b43434eb3237.gif","video_url":"shopify:\/\/pages\/the-new-slimline-leash","category":"AS SEEN ON","category_url":"shopify:\/\/pages\/the-new-slimline-leash","video_description":"How to use the Slimeline leash."}}},"block_order":["c837cd19-ae25-483b-b125-5e1111fb2ea7","b0851cfe-b4c2-4e15-ad4d-3c862a805c9f","a0de07d7-6fd5-4697-9999-39b94d061536","bae59929-35c2-4b81-92eb-1611a576a29f","60e41ea9-c86b-4f06-ac89-7065175dd961","368df2ce-360f-48e8-a858-89226e0db833"],"settings":{"apply_top_padding":true,"apply_bottom_padding":true,"main_title":"Training","content":""}},"f1d739e6-dcdc-4c29-bad7-49de0cddf4cf":{"type":"featured-collection","settings":{"apply_top_padding":false,"apply_bottom_padding":false,"style":"2","collection":"beach","title":"Shop More Training Products","link_url":"shopify:\/\/collections\/dog-training","link_text":"View all"}},"1f681c4b-2fc0-4eeb-a7e8-a7dfb39c1e2d":{"type":"image-with-text","blocks":{"template--21401745359144__1f681c4b-2fc0-4eeb-a7e8-a7dfb39c1e2d-heading-1":{"type":"heading","settings":{"text":"Not sure what the best fit is for your dog?"}},"template--21401745359144__1f681c4b-2fc0-4eeb-a7e8-a7dfb39c1e2d-richtext-1":{"type":"richtext","settings":{"content":"<p>Not sure what the best fit is for your dog?<\/p>"}},"723ec489-b1d2-4485-9b04-eac15476a22a":{"type":"buttons","settings":{"button_1_text":"Size guide","button_1_url":"","button_2_text":"Book a consultation","button_2_url":""}}},"block_order":["template--21401745359144__1f681c4b-2fc0-4eeb-a7e8-a7dfb39c1e2d-heading-1","template--21401745359144__1f681c4b-2fc0-4eeb-a7e8-a7dfb39c1e2d-richtext-1","723ec489-b1d2-4485-9b04-eac15476a22a"],"settings":{"apply_top_padding":true,"apply_bottom_padding":true,"background":"","separate_section_with_border":true,"image":"shopify:\/\/shop_images\/FITTING.jpg","reveal_on_scroll":true,"image_position":"end","content_width":"sm","remove_vertical_spacing":true}}},"order":["main","b40ecaca-8930-44d2-b329-927a7eb05f05","86e20185-14f4-49c7-8d48-b5b46263a128","f1d739e6-dcdc-4c29-bad7-49de0cddf4cf","1f681c4b-2fc0-4eeb-a7e8-a7dfb39c1e2d"]}